odoo_auto_proxy/__init__.py
odoo_auto_proxy/__main__.py
odoo_auto_proxy/args.py
odoo_auto_proxy/certificate.py
odoo_auto_proxy/defaults.py
odoo_auto_proxy/docker_config.py
odoo_auto_proxy/docker_event_listener.py
odoo_auto_proxy/nginx.py
odoo_auto_proxy/utils.py
odoo_auto_proxy/schemas/__init__.py
odoo_auto_proxy/schemas/site.py
odoo_auto_proxy/schemas/tools.py
odoo_auto_proxy/templates/default_certificat.j2
odoo_auto_proxy/templates/site.j2
odoo_auto_proxy-0.1.3.dist-info/LICENSE
odoo_auto_proxy-0.1.3.dist-info/METADATA
odoo_auto_proxy-0.1.3.dist-info/WHEEL
odoo_auto_proxy-0.1.3.dist-info/top_level.txt
odoo_auto_proxy-0.1.3.dist-info/RECORD
