Metadata-Version: 2.1
Name: odoo-auto-proxy
Version: 0.1.3
Summary: Create Reverse Proxy Configuration For Odoo Containers
Home-page: https://github.com/divad1196/odoo_auto_proxy
Author: Gallay David
Author-email: davidtennis96@hotmail.com
License: UNKNOWN
Platform: UNKNOWN
Classifier: Programming Language :: Python :: 3
Classifier: License :: OSI Approved :: MIT License
Classifier: Operating System :: OS Independent
Requires-Dist: certifi (==2021.5.30)
Requires-Dist: chardet (==4.0.0)
Requires-Dist: contextlib2 (==21.6.0)
Requires-Dist: decorator (==5.0.9)
Requires-Dist: docker (==5.0.0)
Requires-Dist: idna (==2.10)
Requires-Dist: Jinja2 (==3.0.1)
Requires-Dist: MarkupSafe (==2.0.1)
Requires-Dist: requests (==2.25.1)
Requires-Dist: schema (==0.7.4)
Requires-Dist: six (==1.16.0)
Requires-Dist: urllib3 (==1.26.6)
Requires-Dist: validators (==0.18.2)
Requires-Dist: websocket-client (==1.1.0)
